{
	"configurations" : 
	[
		{
			"directories" : 
			[
				{
					"build" : ".",
					"minimumCMakeVersion" : 
					{
						"string" : "3.0"
					},
					"projectIndex" : 0,
					"source" : ".",
					"targetIndexes" : 
					[
						0
					]
				}
			],
			"name" : "Debug",
			"projects" : 
			[
				{
					"directoryIndexes" : 
					[
						0
					],
					"name" : "log_test",
					"targetIndexes" : 
					[
						0
					]
				}
			],
			"targets" : 
			[
				{
					"directoryIndex" : 0,
					"id" : "log_test::@6890427a1f51a3e7e1df",
					"jsonFile" : "target-log_test-Debug-2300325ce8254dab61dc.json",
					"name" : "log_test",
					"projectIndex" : 0
				}
			]
		}
	],
	"kind" : "codemodel",
	"paths" : 
	{
		"build" : "/media/data/dev/mav-router-tux/build",
		"source" : "/media/data/dev/mav-router-tux"
	},
	"version" : 
	{
		"major" : 2,
		"minor" : 2
	}
}
